fierce/__init__.py
fierce/fierce.py
fierce/lists/20000.txt
fierce/lists/5000.txt
fierce/lists/__init__.py
fierce/lists/default.txt
fierce-1.6.0.dist-info/LICENSE
fierce-1.6.0.dist-info/METADATA
fierce-1.6.0.dist-info/WHEEL
fierce-1.6.0.dist-info/entry_points.txt
fierce-1.6.0.dist-info/RECORD
