Metadata-Version: 2.1
Name: fierce
Version: 1.6.0
Summary: A DNS reconnaissance tool for locating non-contiguous IP space.
Home-page: https://github.com/mschwager/fierce
License: GPLv3
Requires-Python: >=3.8.1,<4.0.0
Classifier: Environment :: Console
Classifier: Intended Audience :: Information Technology
Classifier: Intended Audience :: System Administrators
Classifier: License :: OSI Approved :: GNU General Public License v3 (GPLv3)
Classifier: License :: Other/Proprietary License
Classifier: Operating System :: MacOS :: MacOS X
Classifier: Operating System :: Microsoft :: Windows
Classifier: Operating System :: POSIX
Classifier: Programming Language :: Python :: 3
Classifier: Programming Language :: Python :: 3.9
Classifier: Programming Language :: Python :: 3.10
Classifier: Programming Language :: Python :: 3.11
Classifier: Programming Language :: Python :: 3.12
Classifier: Programming Language :: Python :: 3.8
Classifier: Topic :: Security
Requires-Dist: dnspython (==1.16.0)
Project-URL: Repository, https://github.com/mschwager/fierce
